[
  {
    "line": 1,
    "elements": [
      {
        "start_timestamp": "2021-03-08T15:29:13.636Z",
        "before": [
          {
            "result": {
              "duration": 1000000,
              "status": "passed"
            },
            "match": {
              "location": "com.vytrack.step_definitions.Hooks.setUp()"
            }
          }
        ],
        "line": 3,
        "name": "Driver user",
        "description": "",
        "id": "account-types;driver-user",
        "after": [
          {
            "result": {
              "error_message": "org.openqa.selenium.WebDriverException: Your OS doesn\u0027t support Safari\nBuild info: version: \u00273.141.59\u0027, revision: \u0027e82be7d358\u0027, time: \u00272018-11-14T08:17:03\u0027\nSystem info: host: \u0027DESKTOP-0F0MCFH\u0027, ip: \u0027192.168.1.5\u0027, os.name: \u0027Windows 10\u0027, os.arch: \u0027amd64\u0027, os.version: \u002710.0\u0027, java.version: \u00271.8.0_281\u0027\nDriver info: driver.version: Driver\r\n\tat com.vytrack.utilities.Driver.get(Driver.java:59)\r\n\tat com.vytrack.step_definitions.Hooks.tearDown(Hooks.java:18)\r\n",
              "duration": 4000000,
              "status": "failed"
            },
            "match": {
              "location": "com.vytrack.step_definitions.Hooks.tearDown(io.cucumber.java.Scenario)"
            }
          }
        ],
        "type": "scenario",
        "keyword": "Scenario",
        "steps": [
          {
            "result": {
              "error_message": "org.openqa.selenium.WebDriverException: Your OS doesn\u0027t support Safari\nBuild info: version: \u00273.141.59\u0027, revision: \u0027e82be7d358\u0027, time: \u00272018-11-14T08:17:03\u0027\nSystem info: host: \u0027DESKTOP-0F0MCFH\u0027, ip: \u0027192.168.1.5\u0027, os.name: \u0027Windows 10\u0027, os.arch: \u0027amd64\u0027, os.version: \u002710.0\u0027, java.version: \u00271.8.0_281\u0027\nDriver info: driver.version: Driver\r\n\tat com.vytrack.utilities.Driver.get(Driver.java:59)\r\n\tat com.vytrack.step_definitions.ContactsStepDefs.the_user_logged_in_as(ContactsStepDefs.java:21)\r\n\tat ✽.the user logged in as \"driver\"(file:///C:/Users/USER/IdeaProjects/EU4CucumberSelenium/src/test/resources/features/AccountTypes.feature:4)\r\n",
              "duration": 9000000,
              "status": "failed"
            },
            "line": 4,
            "name": "the user logged in as \"driver\"",
            "match": {
              "arguments": [
                {
                  "val": "\"driver\"",
                  "offset": 22
                }
              ],
              "location": "com.vytrack.step_definitions.ContactsStepDefs.the_user_logged_in_as(java.lang.String)"
            },
            "keyword": "Given "
          },
          {
            "result": {
              "status": "skipped"
            },
            "line": 5,
            "name": "the user navigates to \"Activities\" \"Calendar Events\"",
            "match": {
              "arguments": [
                {
                  "val": "\"Activities\"",
                  "offset": 22
                },
                {
                  "val": "\"Calendar Events\"",
                  "offset": 35
                }
              ],
              "location": "com.vytrack.step_definitions.LoginStepDefs.the_user_navigates_to(java.lang.String,java.lang.String)"
            },
            "keyword": "When "
          },
          {
            "result": {
              "status": "skipped"
            },
            "line": 6,
            "name": "the title contains \"Calendar Events - Activities\"",
            "match": {
              "arguments": [
                {
                  "val": "\"Calendar Events - Activities\"",
                  "offset": 19
                }
              ],
              "location": "com.vytrack.step_definitions.LoginStepDefs.the_title_contains(java.lang.String)"
            },
            "keyword": "Then "
          }
        ],
        "tags": [
          {
            "name": "@wip"
          },
          {
            "name": "@smoke"
          }
        ]
      },
      {
        "start_timestamp": "2021-03-08T15:29:13.661Z",
        "before": [
          {
            "result": {
              "status": "passed"
            },
            "match": {
              "location": "com.vytrack.step_definitions.Hooks.setUp()"
            }
          }
        ],
        "line": 13,
        "name": "Store manager user",
        "description": "",
        "id": "account-types;store-manager-user",
        "after": [
          {
            "result": {
              "error_message": "org.openqa.selenium.WebDriverException: Your OS doesn\u0027t support Safari\nBuild info: version: \u00273.141.59\u0027, revision: \u0027e82be7d358\u0027, time: \u00272018-11-14T08:17:03\u0027\nSystem info: host: \u0027DESKTOP-0F0MCFH\u0027, ip: \u0027192.168.1.5\u0027, os.name: \u0027Windows 10\u0027, os.arch: \u0027amd64\u0027, os.version: \u002710.0\u0027, java.version: \u00271.8.0_281\u0027\nDriver info: driver.version: Driver\r\n\tat com.vytrack.utilities.Driver.get(Driver.java:59)\r\n\tat com.vytrack.step_definitions.Hooks.tearDown(Hooks.java:18)\r\n",
              "status": "failed"
            },
            "match": {
              "location": "com.vytrack.step_definitions.Hooks.tearDown(io.cucumber.java.Scenario)"
            }
          }
        ],
        "type": "scenario",
        "keyword": "Scenario",
        "steps": [
          {
            "result": {
              "error_message": "org.openqa.selenium.WebDriverException: Your OS doesn\u0027t support Safari\nBuild info: version: \u00273.141.59\u0027, revision: \u0027e82be7d358\u0027, time: \u00272018-11-14T08:17:03\u0027\nSystem info: host: \u0027DESKTOP-0F0MCFH\u0027, ip: \u0027192.168.1.5\u0027, os.name: \u0027Windows 10\u0027, os.arch: \u0027amd64\u0027, os.version: \u002710.0\u0027, java.version: \u00271.8.0_281\u0027\nDriver info: driver.version: Driver\r\n\tat com.vytrack.utilities.Driver.get(Driver.java:59)\r\n\tat com.vytrack.step_definitions.ContactsStepDefs.the_user_logged_in_as(ContactsStepDefs.java:21)\r\n\tat ✽.the user logged in as \"store manager\"(file:///C:/Users/USER/IdeaProjects/EU4CucumberSelenium/src/test/resources/features/AccountTypes.feature:14)\r\n",
              "status": "failed"
            },
            "line": 14,
            "name": "the user logged in as \"store manager\"",
            "match": {
              "arguments": [
                {
                  "val": "\"store manager\"",
                  "offset": 22
                }
              ],
              "location": "com.vytrack.step_definitions.ContactsStepDefs.the_user_logged_in_as(java.lang.String)"
            },
            "keyword": "Given "
          },
          {
            "result": {
              "status": "skipped"
            },
            "line": 15,
            "name": "the user navigates to \"Customers\" \"Contacts\"",
            "match": {
              "arguments": [
                {
                  "val": "\"Customers\"",
                  "offset": 22
                },
                {
                  "val": "\"Contacts\"",
                  "offset": 34
                }
              ],
              "location": "com.vytrack.step_definitions.LoginStepDefs.the_user_navigates_to(java.lang.String,java.lang.String)"
            },
            "keyword": "When "
          },
          {
            "result": {
              "status": "skipped"
            },
            "line": 16,
            "name": "the title contains \"Contacts - Customers\"",
            "match": {
              "arguments": [
                {
                  "val": "\"Contacts - Customers\"",
                  "offset": 19
                }
              ],
              "location": "com.vytrack.step_definitions.LoginStepDefs.the_title_contains(java.lang.String)"
            },
            "keyword": "Then "
          }
        ],
        "tags": [
          {
            "name": "@wip"
          },
          {
            "name": "@smoke"
          }
        ]
      }
    ],
    "name": "Account types",
    "description": "",
    "id": "account-types",
    "keyword": "Feature",
    "uri": "file:src/test/resources/features/AccountTypes.feature",
    "tags": []
  },
  {
    "line": 2,
    "elements": [
      {
        "start_timestamp": "2021-03-08T15:29:13.636Z",
        "before": [
          {
            "result": {
              "duration": 1000000,
              "status": "passed"
            },
            "match": {
              "location": "com.vytrack.step_definitions.Hooks.setUp()"
            }
          }
        ],
        "line": 4,
        "name": "Navigating Fleet -- Vehicles",
        "description": "",
        "id": "navigation-menu;navigating-fleet----vehicles",
        "after": [
          {
            "result": {
              "error_message": "org.openqa.selenium.WebDriverException: Your OS doesn\u0027t support Safari\nBuild info: version: \u00273.141.59\u0027, revision: \u0027e82be7d358\u0027, time: \u00272018-11-14T08:17:03\u0027\nSystem info: host: \u0027DESKTOP-0F0MCFH\u0027, ip: \u0027192.168.1.5\u0027, os.name: \u0027Windows 10\u0027, os.arch: \u0027amd64\u0027, os.version: \u002710.0\u0027, java.version: \u00271.8.0_281\u0027\nDriver info: driver.version: Driver\r\n\tat com.vytrack.utilities.Driver.get(Driver.java:59)\r\n\tat com.vytrack.step_definitions.Hooks.tearDown(Hooks.java:18)\r\n",
              "duration": 1000000,
              "status": "failed"
            },
            "match": {
              "location": "com.vytrack.step_definitions.Hooks.tearDown(io.cucumber.java.Scenario)"
            }
          }
        ],
        "type": "scenario",
        "keyword": "Scenario",
        "steps": [
          {
            "result": {
              "error_message": "org.openqa.selenium.WebDriverException: Your OS doesn\u0027t support Safari\nBuild info: version: \u00273.141.59\u0027, revision: \u0027e82be7d358\u0027, time: \u00272018-11-14T08:17:03\u0027\nSystem info: host: \u0027DESKTOP-0F0MCFH\u0027, ip: \u0027192.168.1.5\u0027, os.name: \u0027Windows 10\u0027, os.arch: \u0027amd64\u0027, os.version: \u002710.0\u0027, java.version: \u00271.8.0_281\u0027\nDriver info: driver.version: Driver\r\n\tat com.vytrack.utilities.Driver.get(Driver.java:59)\r\n\tat com.vytrack.step_definitions.LoginStepDefs.the_user_is_on_the_login_page(LoginStepDefs.java:21)\r\n\tat ✽.the user is on the login page(file:///C:/Users/USER/IdeaProjects/EU4CucumberSelenium/src/test/resources/features/NavigationMenu.feature:5)\r\n",
              "duration": 9000000,
              "status": "failed"
            },
            "line": 5,
            "name": "the user is on the login page",
            "match": {
              "location": "com.vytrack.step_definitions.LoginStepDefs.the_user_is_on_the_login_page()"
            },
            "keyword": "Given "
          },
          {
            "result": {
              "status": "skipped"
            },
            "line": 6,
            "name": "the user enters the sales manager information",
            "match": {
              "location": "com.vytrack.step_definitions.LoginStepDefs.the_user_enters_the_sales_manager_information()"
            },
            "keyword": "And "
          },
          {
            "result": {
              "status": "skipped"
            },
            "line": 7,
            "name": "the user navigates to Fleet, Vehicles",
            "match": {
              "location": "com.vytrack.step_definitions.NavigationMenuStepDefs.the_user_navigates_to_Fleet_Vehicles()"
            },
            "keyword": "When "
          },
          {
            "result": {
              "status": "skipped"
            },
            "line": 8,
            "name": "the title should be Vehicles",
            "match": {
              "location": "com.vytrack.step_definitions.NavigationMenuStepDefs.the_title_should_be_Vehicles()"
            },
            "keyword": "Then "
          }
        ],
        "tags": [
          {
            "name": "@navigate"
          },
          {
            "name": "@vehicles"
          },
          {
            "name": "@sales_manager"
          },
          {
            "name": "@smoke"
          }
        ]
      }
    ],
    "name": "Navigation Menu",
    "description": "",
    "id": "navigation-menu",
    "keyword": "Feature",
    "uri": "file:src/test/resources/features/NavigationMenu.feature",
    "tags": [
      {
        "name": "@navigate",
        "type": "Tag",
        "location": {
          "line": 1,
          "column": 1
        }
      }
    ]
  },
  {
    "line": 2,
    "elements": [
      {
        "line": 4,
        "name": "",
        "description": "",
        "type": "background",
        "keyword": "Background",
        "steps": [
          {
            "result": {
              "error_message": "org.openqa.selenium.WebDriverException: Your OS doesn\u0027t support Safari\nBuild info: version: \u00273.141.59\u0027, revision: \u0027e82be7d358\u0027, time: \u00272018-11-14T08:17:03\u0027\nSystem info: host: \u0027DESKTOP-0F0MCFH\u0027, ip: \u0027192.168.1.5\u0027, os.name: \u0027Windows 10\u0027, os.arch: \u0027amd64\u0027, os.version: \u002710.0\u0027, java.version: \u00271.8.0_281\u0027\nDriver info: driver.version: Driver\r\n\tat com.vytrack.utilities.Driver.get(Driver.java:59)\r\n\tat com.vytrack.step_definitions.LoginStepDefs.the_user_is_on_the_login_page(LoginStepDefs.java:21)\r\n\tat ✽.the user is on the login page(file:///C:/Users/USER/IdeaProjects/EU4CucumberSelenium/src/test/resources/features/login.feature:5)\r\n",
              "duration": 9000000,
              "status": "failed"
            },
            "line": 5,
            "name": "the user is on the login page",
            "match": {
              "location": "com.vytrack.step_definitions.LoginStepDefs.the_user_is_on_the_login_page()"
            },
            "keyword": "Given "
          }
        ]
      },
      {
        "start_timestamp": "2021-03-08T15:29:13.636Z",
        "before": [
          {
            "result": {
              "duration": 1000000,
              "status": "passed"
            },
            "match": {
              "location": "com.vytrack.step_definitions.Hooks.setUp()"
            }
          }
        ],
        "line": 7,
        "name": "Login as a driver",
        "description": "",
        "id": "users-should-be-able-to-login;login-as-a-driver",
        "after": [
          {
            "result": {
              "error_message": "org.openqa.selenium.WebDriverException: Your OS doesn\u0027t support Safari\nBuild info: version: \u00273.141.59\u0027, revision: \u0027e82be7d358\u0027, time: \u00272018-11-14T08:17:03\u0027\nSystem info: host: \u0027DESKTOP-0F0MCFH\u0027, ip: \u0027192.168.1.5\u0027, os.name: \u0027Windows 10\u0027, os.arch: \u0027amd64\u0027, os.version: \u002710.0\u0027, java.version: \u00271.8.0_281\u0027\nDriver info: driver.version: Driver\r\n\tat com.vytrack.utilities.Driver.get(Driver.java:59)\r\n\tat com.vytrack.step_definitions.Hooks.tearDown(Hooks.java:18)\r\n",
              "duration": 4000000,
              "status": "failed"
            },
            "match": {
              "location": "com.vytrack.step_definitions.Hooks.tearDown(io.cucumber.java.Scenario)"
            }
          }
        ],
        "type": "scenario",
        "keyword": "Scenario",
        "steps": [
          {
            "result": {
              "status": "skipped"
            },
            "line": 8,
            "name": "the user enters the driver information",
            "match": {
              "location": "com.vytrack.step_definitions.LoginStepDefs.the_user_enters_the_driver_information()"
            },
            "keyword": "When "
          },
          {
            "result": {
              "status": "skipped"
            },
            "line": 9,
            "name": "the user should be able to login",
            "match": {
              "location": "com.vytrack.step_definitions.LoginStepDefs.the_user_should_be_able_to_login()"
            },
            "keyword": "Then "
          }
        ],
        "tags": [
          {
            "name": "@login"
          },
          {
            "name": "@smoke"
          },
          {
            "name": "@driver"
          },
          {
            "name": "@VYT-123"
          }
        ]
      },
      {
        "line": 4,
        "name": "",
        "description": "",
        "type": "background",
        "keyword": "Background",
        "steps": [
          {
            "result": {
              "error_message": "org.openqa.selenium.WebDriverException: Your OS doesn\u0027t support Safari\nBuild info: version: \u00273.141.59\u0027, revision: \u0027e82be7d358\u0027, time: \u00272018-11-14T08:17:03\u0027\nSystem info: host: \u0027DESKTOP-0F0MCFH\u0027, ip: \u0027192.168.1.5\u0027, os.name: \u0027Windows 10\u0027, os.arch: \u0027amd64\u0027, os.version: \u002710.0\u0027, java.version: \u00271.8.0_281\u0027\nDriver info: driver.version: Driver\r\n\tat com.vytrack.utilities.Driver.get(Driver.java:59)\r\n\tat com.vytrack.step_definitions.LoginStepDefs.the_user_is_on_the_login_page(LoginStepDefs.java:21)\r\n\tat ✽.the user is on the login page(file:///C:/Users/USER/IdeaProjects/EU4CucumberSelenium/src/test/resources/features/login.feature:5)\r\n",
              "duration": 1000000,
              "status": "failed"
            },
            "line": 5,
            "name": "the user is on the login page",
            "match": {
              "location": "com.vytrack.step_definitions.LoginStepDefs.the_user_is_on_the_login_page()"
            },
            "keyword": "Given "
          }
        ]
      },
      {
        "start_timestamp": "2021-03-08T15:29:13.660Z",
        "before": [
          {
            "result": {
              "status": "passed"
            },
            "match": {
              "location": "com.vytrack.step_definitions.Hooks.setUp()"
            }
          }
        ],
        "line": 11,
        "name": "Login as a sales manager",
        "description": "",
        "id": "users-should-be-able-to-login;login-as-a-sales-manager",
        "after": [
          {
            "result": {
              "error_message": "org.openqa.selenium.WebDriverException: Your OS doesn\u0027t support Safari\nBuild info: version: \u00273.141.59\u0027, revision: \u0027e82be7d358\u0027, time: \u00272018-11-14T08:17:03\u0027\nSystem info: host: \u0027DESKTOP-0F0MCFH\u0027, ip: \u0027192.168.1.5\u0027, os.name: \u0027Windows 10\u0027, os.arch: \u0027amd64\u0027, os.version: \u002710.0\u0027, java.version: \u00271.8.0_281\u0027\nDriver info: driver.version: Driver\r\n\tat com.vytrack.utilities.Driver.get(Driver.java:59)\r\n\tat com.vytrack.step_definitions.Hooks.tearDown(Hooks.java:18)\r\n",
              "status": "failed"
            },
            "match": {
              "location": "com.vytrack.step_definitions.Hooks.tearDown(io.cucumber.java.Scenario)"
            }
          }
        ],
        "type": "scenario",
        "keyword": "Scenario",
        "steps": [
          {
            "result": {
              "status": "skipped"
            },
            "line": 12,
            "name": "the user enters the sales manager information",
            "match": {
              "location": "com.vytrack.step_definitions.LoginStepDefs.the_user_enters_the_sales_manager_information()"
            },
            "keyword": "When "
          },
          {
            "result": {
              "status": "skipped"
            },
            "line": 13,
            "name": "the user should be able to login",
            "match": {
              "location": "com.vytrack.step_definitions.LoginStepDefs.the_user_should_be_able_to_login()"
            },
            "keyword": "Then "
          }
        ],
        "tags": [
          {
            "name": "@login"
          },
          {
            "name": "@smoke"
          },
          {
            "name": "@VYT-123"
          }
        ]
      },
      {
        "line": 4,
        "name": "",
        "description": "",
        "type": "background",
        "keyword": "Background",
        "steps": [
          {
            "result": {
              "error_message": "org.openqa.selenium.WebDriverException: Your OS doesn\u0027t support Safari\nBuild info: version: \u00273.141.59\u0027, revision: \u0027e82be7d358\u0027, time: \u00272018-11-14T08:17:03\u0027\nSystem info: host: \u0027DESKTOP-0F0MCFH\u0027, ip: \u0027192.168.1.5\u0027, os.name: \u0027Windows 10\u0027, os.arch: \u0027amd64\u0027, os.version: \u002710.0\u0027, java.version: \u00271.8.0_281\u0027\nDriver info: driver.version: Driver\r\n\tat com.vytrack.utilities.Driver.get(Driver.java:59)\r\n\tat com.vytrack.step_definitions.LoginStepDefs.the_user_is_on_the_login_page(LoginStepDefs.java:21)\r\n\tat ✽.the user is on the login page(file:///C:/Users/USER/IdeaProjects/EU4CucumberSelenium/src/test/resources/features/login.feature:5)\r\n",
              "status": "failed"
            },
            "line": 5,
            "name": "the user is on the login page",
            "match": {
              "location": "com.vytrack.step_definitions.LoginStepDefs.the_user_is_on_the_login_page()"
            },
            "keyword": "Given "
          }
        ]
      },
      {
        "start_timestamp": "2021-03-08T15:29:13.663Z",
        "before": [
          {
            "result": {
              "status": "passed"
            },
            "match": {
              "location": "com.vytrack.step_definitions.Hooks.setUp()"
            }
          }
        ],
        "line": 16,
        "name": "Login as a store manager",
        "description": "",
        "id": "users-should-be-able-to-login;login-as-a-store-manager",
        "after": [
          {
            "result": {
              "error_message": "org.openqa.selenium.WebDriverException: Your OS doesn\u0027t support Safari\nBuild info: version: \u00273.141.59\u0027, revision: \u0027e82be7d358\u0027, time: \u00272018-11-14T08:17:03\u0027\nSystem info: host: \u0027DESKTOP-0F0MCFH\u0027, ip: \u0027192.168.1.5\u0027, os.name: \u0027Windows 10\u0027, os.arch: \u0027amd64\u0027, os.version: \u002710.0\u0027, java.version: \u00271.8.0_281\u0027\nDriver info: driver.version: Driver\r\n\tat com.vytrack.utilities.Driver.get(Driver.java:59)\r\n\tat com.vytrack.step_definitions.Hooks.tearDown(Hooks.java:18)\r\n",
              "status": "failed"
            },
            "match": {
              "location": "com.vytrack.step_definitions.Hooks.tearDown(io.cucumber.java.Scenario)"
            }
          }
        ],
        "type": "scenario",
        "keyword": "Scenario",
        "steps": [
          {
            "result": {
              "status": "skipped"
            },
            "line": 17,
            "name": "the user enters the store manager information",
            "match": {
              "location": "com.vytrack.step_definitions.LoginStepDefs.the_user_enters_the_store_manager_information()"
            },
            "keyword": "When "
          },
          {
            "result": {
              "status": "skipped"
            },
            "line": 18,
            "name": "the user should be able to login",
            "match": {
              "location": "com.vytrack.step_definitions.LoginStepDefs.the_user_should_be_able_to_login()"
            },
            "keyword": "Then "
          }
        ],
        "tags": [
          {
            "name": "@login"
          },
          {
            "name": "@smoke"
          },
          {
            "name": "@store_manager"
          }
        ]
      }
    ],
    "name": "Users should be able to login",
    "description": "",
    "id": "users-should-be-able-to-login",
    "keyword": "Feature",
    "uri": "file:src/test/resources/features/login.feature",
    "tags": [
      {
        "name": "@login",
        "type": "Tag",
        "location": {
          "line": 1,
          "column": 1
        }
      },
      {
        "name": "@smoke",
        "type": "Tag",
        "location": {
          "line": 1,
          "column": 8
        }
      }
    ]
  }
]